controlunit.sv
module controlunit(
    input logic EQ, 
    input logic [31:0] instr,
    output logic RegWrite,
    output logic [2:0] ALUctrl, //changeable depending on amt of ALU instr
    output logic ALUSrc, //high for all except R type
    output logic PCsrc, //high for B type, EQ AND BRANCH
    output logic [2:0] ImmSrc,
    output logic ResultSrc, //determined by signextend unit
    output logic MemWrite
);

logic [2:0] funct3;
logic [1:0] ALUop;

assign funct3 = instr[14:12];
assign  ALUop = instr[1:0];


//main decoder

always_comb begin
case (instr[6:0]) //opcode
    7'b11       :   if (funct3 == 3'b010) //lw
                        begin 
                            RegWrite = 1'b1;
                            ALUSrc = 1'b1;
                            ImmSrc = 3'b0;
                            PCsrc = 0'b0;
                            ResultSrc = 1'b1; 
                            MemWrite = 1'b1;
                        end
    
    7'b0010011  :   if (funct3 == 3'b000) //addi
                        begin
                            RegWrite = 1'b1;
                            ALUSrc = 1'b1;
                            ImmSrc = 3'b0;
                            PCsrc = 1'b0;
                            ResultSrc = 1'b0;
                            MemWrite = 1'b0; 
                        end
    7'b1100011  :  begin if (funct3 == 3'b0) //beq
                        begin
                            RegWrite = 1'b0;
                            ALUSrc = 1'b1;
                            ImmSrc = 3'b11;
                            PCsrc = EQ; 
                            ResultSrc = 1'b0;
                            MemWrite = 1'b0; 
                        end
                    if (funct3 == 3'b1) //bne
                        begin
                            RegWrite = 1'b0;
                            ALUSrc = 1'b1;
                            ImmSrc = 3'b11;
                            PCsrc = ~EQ;
                            ResultSrc = 1'b0;
                            MemWrite = 1'b0; 
                        end
    end

endcase end

//ALU decoder

always_comb begin
case (ALUop)
    2'b0     :  ALUctrl = 3'b0; //lw,sw add
    2'b01    :  ALUctrl = 3'b1; //beq subtract
    2'b10    :  ALUctrl = 3'b0; //add
endcase end
endmodule

data_ram.sv
module data_ram #(
    parameter ADDRESS_WIDTH = 32,
              DATA_WIDTH = 32
)(
    input logic                clk,
    input logic                Data_WE,
    input logic  [ADDRESS_WIDTH -1:0]  Data_addr,
    input logic [DATA_WIDTH -1:0]   Data_WD,
    output logic  [DATA_WIDTH -1:0] Data_RD

);


logic [7:0] data_mem [2**8-1:0];
logic [7:0] short_addr;
assign short_addr = Data_addr[7:0];

initial begin
        $display("Loading Data_mem.");
        $readmemh("data.mem", data_mem);
end;

always_comb begin
    Data_RD = {data_mem[short_addr], 
    data_mem[short_addr + 1], 
    data_mem[short_addr + 2], 
    data_mem[short_addr + 3]};
end

always_ff @(posedge clk)
    if (Data_WE) begin
    data_mem[short_addr] <= Data_WD[31:24];
    data_mem[short_addr + 1] <= Data_WD[23:16];
    data_mem[short_addr + 2] <= Data_WD[15:8];
    data_mem[short_addr + 3] <= Data_WD[7:0];
    end

endmodule

ALU.sv
module ALU #(
    parameter WIDTH = 32
)(  
    input logic [WIDTH -1:0] d0,
    input logic [WIDTH -1:0] d1,
    input logic [2:0] ALUctrl,
    output logic [WIDTH -1:0] dout,
    output logic EQ
);



always_comb begin
    if (d0 == d1) EQ = 1'b1;
    else EQ = 1'b0;
    case (ALUctrl)
        3'b000: dout = d0 + d1;
        3'b001: dout = d0 - d1;
        3'b010: dout = d0 & d1;
        3'b011: dout = d0 | d1;
        3'b101: dout = ( d0 < d1);
    endcase
end
endmodule

signextend.sv
module signextend #(
    parameter DATA_WIDTH = 32
)(
    input logic [DATA_WIDTH-1:0] instr,
    input logic [2:0] ImmSrc, //must be 3 bit as there are 5 differnet types of instructions
    output logic [31:0] ImmOp 
);

always_comb begin
    case(ImmSrc) //different ImmSrc for the 5 different risc-v instruction types
        3'b0    : ImmOp = {{20{instr[31]}}, instr[31:20]}; //immedate
        3'b01   : ImmOp = {{20{instr[31]}}, instr[31:25], instr[11:7]}; // store
        3'b11   : ImmOp = {{20{instr[31]}}, instr[7], instr[30:25], instr[11:8], 1'b0}; //branch
    endcase end

endmodule

RegFile.sv
module RegFile #(
    parameter D_WIDTH = 32,
    parameter A_WIDTH = 5
)(
    input logic clk,
    input logic [A_WIDTH-1:0] AD1,
    input logic [A_WIDTH-1:0] AD2,
    input logic [A_WIDTH-1:0] AD3,
    input logic WE3,
    input logic [D_WIDTH-1:0] WD3,
    output logic [D_WIDTH-1:0] RD1,
    output logic [D_WIDTH-1:0] RD2,
    output logic [D_WIDTH-1:0] a0
);


logic [D_WIDTH-1:0] mem [0: 2**A_WIDTH -1];

initial begin
    mem[0] = 32'b0;
    end

always_comb begin
    RD1 = mem[AD1];
    RD2 = mem[AD2];
    a0 = mem[10];
end

always_ff @( posedge clk ) begin 
    if (WE3) mem[AD3] <= WD3;  
end
endmodule

instrmem.sv
module instrmem #(
    parameter ADDRESS_WIDTH = 32,
    parameter DATA_WIDTH = 32 
)(
    input logic  [ADDRESS_WIDTH-1:0]  A,
    output logic [DATA_WIDTH-1:0]  RD
);

logic [7:0] short_addr; //for this test where a memory of only 8
logic [7:0] rom_array [2**8-1:0]; //dont need the whole 2^32 at this stage

assign short_addr = A[7:0];

initial begin
        $display("Loading rom.");
        $readmemh("memory.mem", rom_array);
end;


always_comb
    RD = {rom_array [short_addr + 8'h3], 
            rom_array [short_addr + 8'h2], 
            rom_array [short_addr + 8'h1], 
            rom_array [short_addr]}; 
endmodule

counter_unit.sv
module counter_unit #(
    parameter PC_WIDTH = 32 // bit of PC
)(
    input  logic clk,
    input  logic rst,
    input  logic PCsrc, //branch or increment
    input  logic [PC_WIDTH-1:0] ImmOp, //offset of branch
    output logic [PC_WIDTH-1:0] PC
);

logic [PC_WIDTH-1:0] inc_PC;
logic [PC_WIDTH-1:0] branch_PC;

assign branch_PC = PC + ImmOp; //compute branch_pc
assign inc_PC = PC + 32'h4;

logic [PC_WIDTH-1:0] next_PC;
assign next_PC <= PCsrc? inc_PC :branch_PC

always_ff @ (posedge clk) begin
  if (rst) PC <= {PC_WIDTH{1'b0}};
  else PC <= next_PC;
end

endmodule

top.sv
module Top #(
    parameter  DATA_WIDTH = 32,
    parameter A_WIDTH = 32
)(
    input  logic clk,
    input  logic rst,
    output logic[31:0] a0,
    output logic [31:0] instr,
    output logic [31:0] PC,
    output logic PCsrc,
    output logic [31:0] ImmOp
);

/* all data path signals are defined at the output of 
components, and all control signals are defined at the
components which they control*/

// Program Counter Unit Signals
    //Data
    /////logic [31:0] PC;
    //Control
    //logic PCsrc;
// Instruction Memory
    //Data
    ///////logic [31:0] instr;
// Register Files
    //Data
    logic [31:0] RD1; 
    logic [31:0] RD2;
    //Control
    logic RegWrite; //write enable
// ALU
    //Data
    logic [31:0] ALUResult;
    logic EQ;
    //Control
    logic [2:0]  ALUctrl;

// Sign Extension Signals 
    //Data
    //logic [31:0] ImmOp;
    //Control
    logic [2:0] ImmSrc;

// ALU mux signals
    //Data
    logic [31:0] ALUop2;
    //Control
    logic ALUSrc;

//Writeback Mux 
    //Data
    logic [31:0] Result;
    logic ResultSrc;

// Data Ram Signals
    //Data
    logic [31:0] ReadData;
    //Control
    logic MemWrite;

counter_unit ProgramCounter (
    .clk(clk),
    .rst(rst),
    .PCsrc(PCsrc),
    .PC(PC),
    .ImmOp(ImmOp)
);

instrmem Instruction(
    .A(PC),
    .RD(instr)
);

RegFile Register (
    .clk(clk),
    .AD1(instr[19:15]),
    .AD2(instr[24:20]),
    .AD3(instr[11:7]),
    .WE3(RegWrite),
    .WD3(Result),
    .RD1(RD1),
    .RD2(RD2),
    .a0(a0)
);

//ALUmux
assign ALUop2 = ALUSrc?ImmOp: RD2;

signextend Extend (
    .instr(instr),
    .ImmSrc(ImmSrc),
    .ImmOp(ImmOp)
);

ALU ALU(
    .d0(RD1),
    .d1(ALUop2),
    .ALUctrl(ALUctrl),
    .EQ(EQ),
    .dout(ALUResult)
);

data_ram data_ram (
    .clk(clk),
    .Data_WE(MemWrite),
    .Data_addr(ALUResult),
    .Data_WD(RD2),
    .Data_RD(ReadData)
);

//Mux for result
assign Result = ResultSrc? ReadData:ALUResult;

controlunit Decode (
    .EQ(EQ),
    .instr(instr),
    .RegWrite(RegWrite),
    .ALUctrl(ALUctrl),
    .ALUSrc(ALUSrc),
    .ImmSrc(ImmSrc),
    .PCsrc(PCsrc),
    .MemWrite(MemWrite),
    .ResultSrc(ResultSrc)
);


endmodule

top.vcd
$version Generated by VerilatedVcd $end
$date Thu Nov 24 19:41:54 2022 $end
$timescale 1ps $end

 $scope module TOP $end
  $var wire 32 W ImmOp [31:0] $end
  $var wire 32 U PC [31:0] $end
  $var wire  1 V PCsrc $end
  $var wire 32 S a0 [31:0] $end
  $var wire  1 Q clk $end
  $var wire 32 T instr [31:0] $end
  $var wire  1 R rst $end
  $scope module Top $end
   $var wire 32 & ALUResult [31:0] $end
   $var wire  1 + ALUSrc $end
   $var wire  3 ( ALUctrl [2:0] $end
   $var wire 32 * ALUop2 [31:0] $end
   $var wire 32 a A_WIDTH [31:0] $end
   $var wire 32 a DATA_WIDTH [31:0] $end
   $var wire  1 ' EQ $end
   $var wire 32 W ImmOp [31:0] $end
   $var wire  3 ) ImmSrc [2:0] $end
   $var wire  1 / MemWrite $end
   $var wire 32 U PC [31:0] $end
   $var wire  1 V PCsrc $end
   $var wire 32 # RD1 [31:0] $end
   $var wire 32 $ RD2 [31:0] $end
   $var wire 32 . ReadData [31:0] $end
   $var wire  1 % RegWrite $end
   $var wire 32 , Result [31:0] $end
   $var wire  1 - ResultSrc $end
   $var wire 32 S a0 [31:0] $end
   $var wire  1 Q clk $end
   $var wire 32 T instr [31:0] $end
   $var wire  1 R rst $end
   $scope module ALU $end
    $var wire  3 ( ALUctrl [2:0] $end
    $var wire  1 ' EQ $end
    $var wire 32 a WIDTH [31:0] $end
    $var wire 32 # d0 [31:0] $end
    $var wire 32 * d1 [31:0] $end
    $var wire 32 & dout [31:0] $end
   $upscope $end
   $scope module Decode $end
    $var wire  1 + ALUSrc $end
    $var wire  3 ( ALUctrl [2:0] $end
    $var wire  2 Y ALUop [1:0] $end
    $var wire  1 ' EQ $end
    $var wire  3 ) ImmSrc [2:0] $end
    $var wire  1 / MemWrite $end
    $var wire  1 V PCsrc $end
    $var wire  1 % RegWrite $end
    $var wire  1 - ResultSrc $end
    $var wire  3 X funct3 [2:0] $end
    $var wire 32 T instr [31:0] $end
   $upscope $end
   $scope module Extend $end
    $var wire 32 a DATA_WIDTH [31:0] $end
    $var wire 32 W ImmOp [31:0] $end
    $var wire  3 ) ImmSrc [2:0] $end
    $var wire 32 T instr [31:0] $end
   $upscope $end
   $scope module Instruction $end
    $var wire 32 U A [31:0] $end
    $var wire 32 a ADDRESS_WIDTH [31:0] $end
    $var wire 32 a DATA_WIDTH [31:0] $end
    $var wire 32 T RD [31:0] $end
    $var wire  8 Z short_addr [7:0] $end
   $upscope $end
   $scope module ProgramCounter $end
    $var wire 32 W ImmOp [31:0] $end
    $var wire 32 U PC [31:0] $end
    $var wire 32 a PC_WIDTH [31:0] $end
    $var wire  1 V PCsrc $end
    $var wire 32 \ branch_PC [31:0] $end
    $var wire  1 Q clk $end
    $var wire 32 [ inc_PC [31:0] $end
    $var wire 32 ] next_PC [31:0] $end
    $var wire  1 R rst $end
   $upscope $end
   $scope module Register $end
    $var wire  5 ^ AD1 [4:0] $end
    $var wire  5 _ AD2 [4:0] $end
    $var wire  5 ` AD3 [4:0] $end
    $var wire 32 b A_WIDTH [31:0] $end
    $var wire 32 a D_WIDTH [31:0] $end
    $var wire 32 # RD1 [31:0] $end
    $var wire 32 $ RD2 [31:0] $end
    $var wire 32 , WD3 [31:0] $end
    $var wire  1 % WE3 $end
    $var wire 32 S a0 [31:0] $end
    $var wire  1 Q clk $end
    $var wire 32 0 mem[0] [31:0] $end
    $var wire 32 : mem[10] [31:0] $end
    $var wire 32 ; mem[11] [31:0] $end
    $var wire 32 < mem[12] [31:0] $end
    $var wire 32 = mem[13] [31:0] $end
    $var wire 32 > mem[14] [31:0] $end
    $var wire 32 ? mem[15] [31:0] $end
    $var wire 32 @ mem[16] [31:0] $end
    $var wire 32 A mem[17] [31:0] $end
    $var wire 32 B mem[18] [31:0] $end
    $var wire 32 C mem[19] [31:0] $end
    $var wire 32 1 mem[1] [31:0] $end
    $var wire 32 D mem[20] [31:0] $end
    $var wire 32 E mem[21] [31:0] $end
    $var wire 32 F mem[22] [31:0] $end
    $var wire 32 G mem[23] [31:0] $end
    $var wire 32 H mem[24] [31:0] $end
    $var wire 32 I mem[25] [31:0] $end
    $var wire 32 J mem[26] [31:0] $end
    $var wire 32 K mem[27] [31:0] $end
    $var wire 32 L mem[28] [31:0] $end
    $var wire 32 M mem[29] [31:0] $end
    $var wire 32 2 mem[2] [31:0] $end
    $var wire 32 N mem[30] [31:0] $end
    $var wire 32 O mem[31] [31:0] $end
    $var wire 32 3 mem[3] [31:0] $end
    $var wire 32 4 mem[4] [31:0] $end
    $var wire 32 5 mem[5] [31:0] $end
    $var wire 32 6 mem[6] [31:0] $end
    $var wire 32 7 mem[7] [31:0] $end
    $var wire 32 8 mem[8] [31:0] $end
    $var wire 32 9 mem[9] [31:0] $end
   $upscope $end
   $scope module data_ram $end
    $var wire 32 a ADDRESS_WIDTH [31:0] $end
    $var wire 32 a DATA_WIDTH [31:0] $end
    $var wire 32 . Data_RD [31:0] $end
    $var wire 32 $ Data_WD [31:0] $end
    $var wire  1 / Data_WE $end
    $var wire 32 & Data_addr [31:0] $end
    $var wire  1 Q clk $end
    $var wire  8 P short_addr [7:0] $end
   $upscope $end
  $upscope $end
 $upscope $end
$enddefinitions $end


#0
b00000000000000000000000000000000 #
b00000000000000000000000000000000 $
0%
b00000000000000000000000000000000 &
0'
b000 (
b000 )
b00000000000000000000000000000000 *
0+
b00000000000000000000000000000000 ,
0-
b00000000000000000000000000000000 .
0/
b00000000000000000000000000000000 0
b00000000000000000000000000000000 1
b00000000000000000000000000000000 2
b00000000000000000000000000000000 3
b00000000000000000000000000000000 4
b00000000000000000000000000000000 5
b00000000000000000000000000000000 6
b00000000000000000000000000000000 7
b00000000000000000000000000000000 8
b00000000000000000000000000000000 9
b00000000000000000000000000000000 :
b00000000000000000000000000000000 ;
b00000000000000000000000000000000 <
b00000000000000000000000000000000 =
b00000000000000000000000000000000 >
b00000000000000000000000000000000 ?
b00000000000000000000000000000000 @
b00000000000000000000000000000000 A
b00000000000000000000000000000000 B
b00000000000000000000000000000000 C
b00000000000000000000000000000000 D
b00000000000000000000000000000000 E
b00000000000000000000000000000000 F
b00000000000000000000000000000000 G
b00000000000000000000000000000000 H
b00000000000000000000000000000000 I
b00000000000000000000000000000000 J
b00000000000000000000000000000000 K
b00000000000000000000000000000000 L
b00000000000000000000000000000000 M
b00000000000000000000000000000000 N
b00000000000000000000000000000000 O
b00000000 P
1Q
0R
b00000000000000000000000000000000 S
b00000000000000000000000000000000 T
b00000000000000000000000000000000 U
0V
b00000000000000000000000000000000 W
b000 X
b00 Y
b00000000 Z
b00000000000000000000000000000100 [
b00000000000000000000000000000000 \
b00000000000000000000000000000100 ]
b00000 ^
b00000 _
b00000 `
b00000000000000000000000000100000 a
b00000000000000000000000000000101 b
#1
1%
b00000000000000000000000011111111 &
b00000000000000000000000011111111 *
1+
b00000000000000000000000011111111 ,
b00000000111111101111110111111101 .
b11111111 P
0Q
b00001111111100000000001100010011 T
b00000000000000000000000011111111 W
b11 Y
b00000000000000000000000011111111 \
b11111 _
b00110 `
#2
b00000000000000000000000000000000 &
1'
b00000000000000000000000000000000 *
b00000000000000000000000000000000 ,
b11111110111111011111110111111101 .
b00000000000000000000000011111111 6
b00000000 P
1Q
b00000000000000000000010100010011 T
b00000000000000000000000000000100 U
b00000000000000000000000000000000 W
b00000100 Z
b00000000000000000000000000001000 [
b00000000000000000000000000000100 \
b00000000000000000000000000001000 ]
b00000 _
b01010 `
#3
0Q
#4
1Q
b00000000000000000000010110010011 T
b00000000000000000000000000001000 U
b00001000 Z
b00000000000000000000000000001100 [
b00000000000000000000000000001000 \
b00000000000000000000000000001100 ]
b01011 `
#5
0Q
#6
b11111110111111011111110111111101 ,
1-
1/
1Q
b00000000000001011010010100000011 T
b00000000000000000000000000001100 U
b010 X
b00001100 Z
b00000000000000000000000000010000 [
b00000000000000000000000000001100 \
b00000000000000000000000000010000 ]
b01011 ^
b01010 `
#7
0Q
#8
b00000000000000000000000000000001 &
0'
b00000000000000000000000000000001 *
b00000000000000000000000000000001 ,
0-
b00000000000000000000000011111101 .
0/
b11111110111111011111110111111101 :
b00000001 P
1Q
b11111110111111011111110111111101 S
b00000000000101011000010110010011 T
b00000000000000000000000000010000 U
b00000000000000000000000000000001 W
b000 X
b00010000 Z
b00000000000000000000000000010100 [
b00000000000000000000000000010001 \
b00000000000000000000000000010100 ]
b00001 _
b01011 `
#9
0Q
#10
b00000000000000000000000000000001 #
b00000000000000000000000011111111 $
0%
b11111111111111111111111111111001 &
b011 )
b11111111111111111111111111111000 *
b11111111111111111111111111111001 ,
b11111100111111001111110111111101 .
b00000000000000000000000000000001 ;
b11111001 P
1Q
b11111110011001011001110011100011 T
b00000000000000000000000000010100 U
1V
b11111111111111111111111111111000 W
b001 X
b00010100 Z
b00000000000000000000000000011000 [
b00000000000000000000000000001100 \
b00000000000000000000000000001100 ]
b00110 _
b11001 `
#11
0Q
#12
b00000000000000000000000000000000 $
1%
b00000000000000000000000000000001 &
b000 )
b00000000000000000000000000000000 *
b00000000000000000000000011111101 ,
1-
b00000000000000000000000011111101 .
1/
b00000001 P
1Q
b00000000000001011010010100000011 T
b00000000000000000000000000001100 U
0V
b00000000000000000000000000000000 W
b010 X
b00001100 Z
b00000000000000000000000000010000 [
b00000000000000000000000000010000 ]
b00000 _
b01010 `
#13
0Q
#14
b00000000000000000000000000000010 &
1'
b00000000000000000000000000000001 *
b00000000000000000000000000000010 ,
0-
0/
b00000000000000000000000011111101 :
b00000010 P
1Q
b00000000000000000000000011111101 S
b00000000000101011000010110010011 T
b00000000000000000000000000010000 U
b00000000000000000000000000000001 W
b000 X
b00010000 Z
b00000000000000000000000000010100 [
b00000000000000000000000000010001 \
b00000000000000000000000000010100 ]
b00001 _
b01011 `
#15
0Q
#16
b00000000000000000000000000000010 #
b00000000000000000000000011111111 $
0%
b11111111111111111111111111111010 &
0'
b011 )
b11111111111111111111111111111000 *
b11111111111111111111111111111010 ,
b11111100111111011111110111111101 .
b00000000000000000000000000000010 ;
b11111010 P
1Q
b11111110011001011001110011100011 T
b00000000000000000000000000010100 U
1V
b11111111111111111111111111111000 W
b001 X
b00010100 Z
b00000000000000000000000000011000 [
b00000000000000000000000000001100 \
b00000000000000000000000000001100 ]
b00110 _
b11001 `
#17
0Q
#18
b00000000000000000000000000000000 $
1%
b00000000000000000000000000000010 &
b000 )
b00000000000000000000000000000000 *
b00000000000000000000000011111101 ,
1-
b00000000000000000000000011111101 .
1/
b00000010 P
1Q
b00000000000001011010010100000011 T
b00000000000000000000000000001100 U
0V
b00000000000000000000000000000000 W
b010 X
b00001100 Z
b00000000000000000000000000010000 [
b00000000000000000000000000010000 ]
b00000 _
b01010 `
#19
0Q
#20
b00000000000000000000000000000011 &
b00000000000000000000000000000001 *
b00000000000000000000000000000011 ,
0-
b00000000000000000000000011111100 .
0/
b00000011 P
1Q
b00000000000101011000010110010011 T
b00000000000000000000000000010000 U
b00000000000000000000000000000001 W
b000 X
b00010000 Z
b00000000000000000000000000010100 [
b00000000000000000000000000010001 \
b00000000000000000000000000010100 ]
b00001 _
b01011 `
#21
0Q
#22
b00000000000000000000000000000011 #
b00000000000000000000000011111111 $
0%
b11111111111111111111111111111011 &
b011 )
b11111111111111111111111111111000 *
b11111111111111111111111111111011 ,
b11111101111111011111110111111101 .
b00000000000000000000000000000011 ;
b11111011 P
1Q
b11111110011001011001110011100011 T
b00000000000000000000000000010100 U
1V
b11111111111111111111111111111000 W
b001 X
b00010100 Z
b00000000000000000000000000011000 [
b00000000000000000000000000001100 \
b00000000000000000000000000001100 ]
b00110 _
b11001 `
#23
0Q
#24
b00000000000000000000000000000000 $
1%
b00000000000000000000000000000011 &
b000 )
b00000000000000000000000000000000 *
b00000000000000000000000011111100 ,
1-
b00000000000000000000000011111100 .
1/
b00000011 P
1Q
b00000000000001011010010100000011 T
b00000000000000000000000000001100 U
0V
b00000000000000000000000000000000 W
b010 X
b00001100 Z
b00000000000000000000000000010000 [
b00000000000000000000000000010000 ]
b00000 _
b01010 `
#25
0Q
#26
b00000000000000000000000000000100 &
b00000000000000000000000000000001 *
b00000000000000000000000000000100 ,
0-
0/
b00000000000000000000000011111100 :
b00000100 P
1Q
b00000000000000000000000011111100 S
b00000000000101011000010110010011 T
b00000000000000000000000000010000 U
b00000000000000000000000000000001 W
b000 X
b00010000 Z
b00000000000000000000000000010100 [
b00000000000000000000000000010001 \
b00000000000000000000000000010100 ]
b00001 _
b01011 `
#27
0Q
#28
b00000000000000000000000000000100 #
b00000000000000000000000011111111 $
0%
b11111111111111111111111111111100 &
b011 )
b11111111111111111111111111111000 *
b11111111111111111111111111111100 ,
b11111101111111011111110100000000 .
b00000000000000000000000000000100 ;
b11111100 P
1Q
b11111110011001011001110011100011 T
b00000000000000000000000000010100 U
1V
b11111111111111111111111111111000 W
b001 X
b00010100 Z
b00000000000000000000000000011000 [
b00000000000000000000000000001100 \
b00000000000000000000000000001100 ]
b00110 _
b11001 `
#29
0Q
#30
b00000000000000000000000000000000 $
1%
b00000000000000000000000000000100 &
b000 )
b00000000000000000000000000000000 *
b00000000000000000000000011111100 ,
1-
b00000000000000000000000011111100 .
1/
b00000100 P
1Q
b00000000000001011010010100000011 T
b00000000000000000000000000001100 U
0V
b00000000000000000000000000000000 W
b010 X
b00001100 Z
b00000000000000000000000000010000 [
b00000000000000000000000000010000 ]
b00000 _
b01010 `
#31
0Q
#32
b00000000000000000000000000000101 &
b00000000000000000000000000000001 *
b00000000000000000000000000000101 ,
0-
b00000000000000000000000011111011 .
0/
b00000101 P
1Q
b00000000000101011000010110010011 T
b00000000000000000000000000010000 U
b00000000000000000000000000000001 W
b000 X
b00010000 Z
b00000000000000000000000000010100 [
b00000000000000000000000000010001 \
b00000000000000000000000000010100 ]
b00001 _
b01011 `
#33
0Q
#34
b00000000000000000000000000000101 #
b00000000000000000000000011111111 $
0%
b11111111111111111111111111111101 &
b011 )
b11111111111111111111111111111000 *
b11111111111111111111111111111101 ,
b11111101111111010000000000000000 .
b00000000000000000000000000000101 ;
b11111101 P
1Q
b11111110011001011001110011100011 T
b00000000000000000000000000010100 U
1V
b11111111111111111111111111111000 W
b001 X
b00010100 Z
b00000000000000000000000000011000 [
b00000000000000000000000000001100 \
b00000000000000000000000000001100 ]
b00110 _
b11001 `
#35
0Q
#36
b00000000000000000000000000000000 $
1%
b00000000000000000000000000000101 &
b000 )
b00000000000000000000000000000000 *
b00000000000000000000000011111011 ,
1-
b00000000000000000000000011111011 .
1/
b00000101 P
1Q
b00000000000001011010010100000011 T
b00000000000000000000000000001100 U
0V
b00000000000000000000000000000000 W
b010 X
b00001100 Z
b00000000000000000000000000010000 [
b00000000000000000000000000010000 ]
b00000 _
b01010 `
#37
0Q
#38
b00000000000000000000000000000110 &
b00000000000000000000000000000001 *
b00000000000000000000000000000110 ,
0-
b00000000000000000000000011111010 .
0/
b00000000000000000000000011111011 :
b00000110 P
1Q
b00000000000000000000000011111011 S
b00000000000101011000010110010011 T
b00000000000000000000000000010000 U
b00000000000000000000000000000001 W
b000 X
b00010000 Z
b00000000000000000000000000010100 [
b00000000000000000000000000010001 \
b00000000000000000000000000010100 ]
b00001 _
b01011 `
#39
0Q
#40
b00000000000000000000000000000110 #
b00000000000000000000000011111111 $
0%
b11111111111111111111111111111110 &
b011 )
b11111111111111111111111111111000 *
b11111111111111111111111111111110 ,
b11111101000000000000000000000000 .
b00000000000000000000000000000110 ;
b11111110 P
1Q
b11111110011001011001110011100011 T
b00000000000000000000000000010100 U
1V
b11111111111111111111111111111000 W
b001 X
b00010100 Z
b00000000000000000000000000011000 [
b00000000000000000000000000001100 \
b00000000000000000000000000001100 ]
b00110 _
b11001 `
#41
0Q
#42
b00000000000000000000000000000000 $
1%
b00000000000000000000000000000110 &
b000 )
b00000000000000000000000000000000 *
b00000000000000000000000011111010 ,
1-
b00000000000000000000000011111010 .
1/
b00000110 P
1Q
b00000000000001011010010100000011 T
b00000000000000000000000000001100 U
0V
b00000000000000000000000000000000 W
b010 X
b00001100 Z
b00000000000000000000000000010000 [
b00000000000000000000000000010000 ]
b00000 _
b01010 `
#43
0Q
#44
b00000000000000000000000000000111 &
b00000000000000000000000000000001 *
b00000000000000000000000000000111 ,
0-
0/
b00000000000000000000000011111010 :
b00000111 P
1Q
b00000000000000000000000011111010 S
b00000000000101011000010110010011 T
b00000000000000000000000000010000 U
b00000000000000000000000000000001 W
b000 X
b00010000 Z
b00000000000000000000000000010100 [
b00000000000000000000000000010001 \
b00000000000000000000000000010100 ]
b00001 _
b01011 `
#45
0Q
#46
b00000000000000000000000000000111 #
b00000000000000000000000011111111 $
0%
b11111111111111111111111111111111 &
b011 )
b11111111111111111111111111111000 *
b11111111111111111111111111111111 ,
b00000000000000000000000000000000 .
b00000000000000000000000000000111 ;
b11111111 P
1Q
b11111110011001011001110011100011 T
b00000000000000000000000000010100 U
1V
b11111111111111111111111111111000 W
b001 X
b00010100 Z
b00000000000000000000000000011000 [
b00000000000000000000000000001100 \
b00000000000000000000000000001100 ]
b00110 _
b11001 `
#47
0Q
#48
b00000000000000000000000000000000 $
1%
b00000000000000000000000000000111 &
b000 )
b00000000000000000000000000000000 *
b00000000000000000000000011111010 ,
1-
b00000000000000000000000011111010 .
1/
b00000111 P
1Q
b00000000000001011010010100000011 T
b00000000000000000000000000001100 U
0V
b00000000000000000000000000000000 W
b010 X
b00001100 Z
b00000000000000000000000000010000 [
b00000000000000000000000000010000 ]
b00000 _
b01010 `
#49
0Q
#50
b00000000000000000000000000001000 &
b00000000000000000000000000000001 *
b00000000000000000000000000001000 ,
0-
b00000000000000000000000011111001 .
0/
b00001000 P
1Q
b00000000000101011000010110010011 T
b00000000000000000000000000010000 U
b00000000000000000000000000000001 W
b000 X
b00010000 Z
b00000000000000000000000000010100 [
b00000000000000000000000000010001 \
b00000000000000000000000000010100 ]
b00001 _
b01011 `
#51
0Q
#52
b00000000000000000000000000001000 #
b00000000000000000000000011111111 $
0%
b00000000000000000000000000000000 &
b011 )
b11111111111111111111111111111000 *
b00000000000000000000000000000000 ,
b00000000000000000000000000000000 .
b00000000000000000000000000001000 ;
b00000000 P
1Q
b11111110011001011001110011100011 T
b00000000000000000000000000010100 U
1V
b11111111111111111111111111111000 W
b001 X
b00010100 Z
b00000000000000000000000000011000 [
b00000000000000000000000000001100 \
b00000000000000000000000000001100 ]
b00110 _
b11001 `
#53
0Q
#54
b00000000000000000000000000000000 $
1%
b00000000000000000000000000001000 &
b000 )
b00000000000000000000000000000000 *
b00000000000000000000000011111001 ,
1-
b00000000000000000000000011111001 .
1/
b00001000 P
1Q
b00000000000001011010010100000011 T
b00000000000000000000000000001100 U
0V
b00000000000000000000000000000000 W
b010 X
b00001100 Z
b00000000000000000000000000010000 [
b00000000000000000000000000010000 ]
b00000 _
b01010 `
#55
0Q
#56
b00000000000000000000000000001001 &
b00000000000000000000000000000001 *
b00000000000000000000000000001001 ,
0-
b00000000000000000000000011111000 .
0/
b00000000000000000000000011111001 :
b00001001 P
1Q
b00000000000000000000000011111001 S
b00000000000101011000010110010011 T
b00000000000000000000000000010000 U
b00000000000000000000000000000001 W
b000 X
b00010000 Z
b00000000000000000000000000010100 [
b00000000000000000000000000010001 \
b00000000000000000000000000010100 ]
b00001 _
b01011 `
#57
0Q
#58
b00000000000000000000000000001001 #
b00000000000000000000000011111111 $
0%
b00000000000000000000000000000001 &
b011 )
b11111111111111111111111111111000 *
b00000000000000000000000000000001 ,
b00000000000000000000000000000000 .
b00000000000000000000000000001001 ;
b00000001 P
1Q
b11111110011001011001110011100011 T
b00000000000000000000000000010100 U
1V
b11111111111111111111111111111000 W
b001 X
b00010100 Z
b00000000000000000000000000011000 [
b00000000000000000000000000001100 \
b00000000000000000000000000001100 ]
b00110 _
b11001 `
#59
0Q
#60
b00000000000000000000000000000000 $
1%
b00000000000000000000000000001001 &
b000 )
b00000000000000000000000000000000 *
b00000000000000000000000011111000 ,
1-
b00000000000000000000000011111000 .
1/
b00001001 P
1Q
b00000000000001011010010100000011 T
b00000000000000000000000000001100 U
0V
b00000000000000000000000000000000 W
b010 X
b00001100 Z
b00000000000000000000000000010000 [
b00000000000000000000000000010000 ]
b00000 _
b01010 `
#61
0Q
#62
b00000000000000000000000000001010 &
b00000000000000000000000000000001 *
b00000000000000000000000000001010 ,
0-
b00000000000000000000000011110111 .
0/
b00000000000000000000000011111000 :
b00001010 P
1Q
b00000000000000000000000011111000 S
b00000000000101011000010110010011 T
b00000000000000000000000000010000 U
b00000000000000000000000000000001 W
b000 X
b00010000 Z
b00000000000000000000000000010100 [
b00000000000000000000000000010001 \
b00000000000000000000000000010100 ]
b00001 _
b01011 `
#63
0Q
#64
b00000000000000000000000000001010 #
b00000000000000000000000011111111 $
0%
b00000000000000000000000000000010 &
b011 )
b11111111111111111111111111111000 *
b00000000000000000000000000000010 ,
b00000000000000000000000000000000 .
b00000000000000000000000000001010 ;
b00000010 P
1Q
b11111110011001011001110011100011 T
b00000000000000000000000000010100 U
1V
b11111111111111111111111111111000 W
b001 X
b00010100 Z
b00000000000000000000000000011000 [
b00000000000000000000000000001100 \
b00000000000000000000000000001100 ]
b00110 _
b11001 `
#65
0Q
